<?xml version="1.0" encoding="UTF-8"?>
<!DOCTYPE mapper PUBLIC "-//mybatis.org//DTD Mapper 3.0//EN" "http://mybatis.org/dtd/mybatis-3-mapper.dtd">
<mapper namespace="com.my.color.wait.dao.WaitDealMapper">
  <resultMap id="BaseResultMap" type="com.my.color.wait.dao.po.WaitDeal">
    <!--
      WARNING - @mbg.generated
      This element is automatically generated by MyBatis Generator, do not modify.
    -->
    <id column="wait_deal_id" jdbcType="VARCHAR" property="waitDealId" />
    <result column="wait_reference_id" jdbcType="VARCHAR" property="waitReferenceId" />
    <result column="wait_instructor_uid" jdbcType="VARCHAR" property="waitInstructorUid" />
    <result column="wait_instructor_uname" jdbcType="VARCHAR" property="waitInstructorUname" />
    <result column="wait_student_uid" jdbcType="VARCHAR" property="waitStudentUid" />
    <result column="wait_student_uname" jdbcType="VARCHAR" property="waitStudentUname" />
    <result column="wait_class_id" jdbcType="VARCHAR" property="waitClassId" />
    <result column="wait_class_name" jdbcType="VARCHAR" property="waitClassName" />
    <result column="wait_is_vaild" jdbcType="VARCHAR" property="waitIsVaild" />
    <result column="wait_deal_state" jdbcType="VARCHAR" property="waitDealState" />
    <result column="wait_create_time" jdbcType="VARCHAR" property="waitCreateTime" />
    <result column="wait_reply_result" jdbcType="VARCHAR" property="waitReplyResult" />
    <result column="wait_reply_time" jdbcType="VARCHAR" property="waitReplyTime" />
  </resultMap>
  <sql id="Base_Column_List">
    <!--
      WARNING - @mbg.generated
      This element is automatically generated by MyBatis Generator, do not modify.
    -->
    wait_deal_id, wait_reference_id, wait_instructor_uid, wait_instructor_uname, wait_student_uid, 
    wait_student_uname, wait_class_id, wait_class_name, wait_is_vaild, wait_deal_state, 
    wait_create_time, wait_reply_result, wait_reply_time
  </sql>
  <select id="selectByPrimaryKey" parameterType="java.lang.String" resultMap="BaseResultMap">
    <!--
      WARNING - @mbg.generated
      This element is automatically generated by MyBatis Generator, do not modify.
    -->
    select 
    <include refid="Base_Column_List" />
    from e_wait_deal
    where wait_deal_id = #{waitDealId,jdbcType=VARCHAR}
  </select>
  <delete id="deleteByPrimaryKey" parameterType="java.lang.String">
    <!--
      WARNING - @mbg.generated
      This element is automatically generated by MyBatis Generator, do not modify.
    -->
    delete from e_wait_deal
    where wait_deal_id = #{waitDealId,jdbcType=VARCHAR}
  </delete>
  <insert id="insert" parameterType="com.my.color.wait.dao.po.WaitDeal">
    <!--
      WARNING - @mbg.generated
      This element is automatically generated by MyBatis Generator, do not modify.
    -->
    insert into e_wait_deal (wait_deal_id, wait_reference_id, wait_instructor_uid, 
      wait_instructor_uname, wait_student_uid, wait_student_uname, 
      wait_class_id, wait_class_name, wait_is_vaild, 
      wait_deal_state, wait_create_time, wait_reply_result, 
      wait_reply_time)
    values (#{waitDealId,jdbcType=VARCHAR}, #{waitReferenceId,jdbcType=VARCHAR}, #{waitInstructorUid,jdbcType=VARCHAR}, 
      #{waitInstructorUname,jdbcType=VARCHAR}, #{waitStudentUid,jdbcType=VARCHAR}, #{waitStudentUname,jdbcType=VARCHAR}, 
      #{waitClassId,jdbcType=VARCHAR}, #{waitClassName,jdbcType=VARCHAR}, #{waitIsVaild,jdbcType=VARCHAR}, 
      #{waitDealState,jdbcType=VARCHAR}, #{waitCreateTime,jdbcType=VARCHAR}, #{waitReplyResult,jdbcType=VARCHAR}, 
      #{waitReplyTime,jdbcType=VARCHAR})
  </insert>
  <insert id="insertSelective" parameterType="com.my.color.wait.dao.po.WaitDeal">
    <!--
      WARNING - @mbg.generated
      This element is automatically generated by MyBatis Generator, do not modify.
    -->
    insert into e_wait_deal
    <trim prefix="(" suffix=")" suffixOverrides=",">
      <if test="waitDealId != null">
        wait_deal_id,
      </if>
      <if test="waitReferenceId != null">
        wait_reference_id,
      </if>
      <if test="waitInstructorUid != null">
        wait_instructor_uid,
      </if>
      <if test="waitInstructorUname != null">
        wait_instructor_uname,
      </if>
      <if test="waitStudentUid != null">
        wait_student_uid,
      </if>
      <if test="waitStudentUname != null">
        wait_student_uname,
      </if>
      <if test="waitClassId != null">
        wait_class_id,
      </if>
      <if test="waitClassName != null">
        wait_class_name,
      </if>
      <if test="waitIsVaild != null">
        wait_is_vaild,
      </if>
      <if test="waitDealState != null">
        wait_deal_state,
      </if>
      <if test="waitCreateTime != null">
        wait_create_time,
      </if>
      <if test="waitReplyResult != null">
        wait_reply_result,
      </if>
      <if test="waitReplyTime != null">
        wait_reply_time,
      </if>
    </trim>
    <trim prefix="values (" suffix=")" suffixOverrides=",">
      <if test="waitDealId != null">
        #{waitDealId,jdbcType=VARCHAR},
      </if>
      <if test="waitReferenceId != null">
        #{waitReferenceId,jdbcType=VARCHAR},
      </if>
      <if test="waitInstructorUid != null">
        #{waitInstructorUid,jdbcType=VARCHAR},
      </if>
      <if test="waitInstructorUname != null">
        #{waitInstructorUname,jdbcType=VARCHAR},
      </if>
      <if test="waitStudentUid != null">
        #{waitStudentUid,jdbcType=VARCHAR},
      </if>
      <if test="waitStudentUname != null">
        #{waitStudentUname,jdbcType=VARCHAR},
      </if>
      <if test="waitClassId != null">
        #{waitClassId,jdbcType=VARCHAR},
      </if>
      <if test="waitClassName != null">
        #{waitClassName,jdbcType=VARCHAR},
      </if>
      <if test="waitIsVaild != null">
        #{waitIsVaild,jdbcType=VARCHAR},
      </if>
      <if test="waitDealState != null">
        #{waitDealState,jdbcType=VARCHAR},
      </if>
      <if test="waitCreateTime != null">
        #{waitCreateTime,jdbcType=VARCHAR},
      </if>
      <if test="waitReplyResult != null">
        #{waitReplyResult,jdbcType=VARCHAR},
      </if>
      <if test="waitReplyTime != null">
        #{waitReplyTime,jdbcType=VARCHAR},
      </if>
    </trim>
  </insert>
  <update id="updateByPrimaryKeySelective" parameterType="com.my.color.wait.dao.po.WaitDeal">
    <!--
      WARNING - @mbg.generated
      This element is automatically generated by MyBatis Generator, do not modify.
    -->
    update e_wait_deal
    <set>
      <if test="waitReferenceId != null">
        wait_reference_id = #{waitReferenceId,jdbcType=VARCHAR},
      </if>
      <if test="waitInstructorUid != null">
        wait_instructor_uid = #{waitInstructorUid,jdbcType=VARCHAR},
      </if>
      <if test="waitInstructorUname != null">
        wait_instructor_uname = #{waitInstructorUname,jdbcType=VARCHAR},
      </if>
      <if test="waitStudentUid != null">
        wait_student_uid = #{waitStudentUid,jdbcType=VARCHAR},
      </if>
      <if test="waitStudentUname != null">
        wait_student_uname = #{waitStudentUname,jdbcType=VARCHAR},
      </if>
      <if test="waitClassId != null">
        wait_class_id = #{waitClassId,jdbcType=VARCHAR},
      </if>
      <if test="waitClassName != null">
        wait_class_name = #{waitClassName,jdbcType=VARCHAR},
      </if>
      <if test="waitIsVaild != null">
        wait_is_vaild = #{waitIsVaild,jdbcType=VARCHAR},
      </if>
      <if test="waitDealState != null">
        wait_deal_state = #{waitDealState,jdbcType=VARCHAR},
      </if>
      <if test="waitCreateTime != null">
        wait_create_time = #{waitCreateTime,jdbcType=VARCHAR},
      </if>
      <if test="waitReplyResult != null">
        wait_reply_result = #{waitReplyResult,jdbcType=VARCHAR},
      </if>
      <if test="waitReplyTime != null">
        wait_reply_time = #{waitReplyTime,jdbcType=VARCHAR},
      </if>
    </set>
    where wait_deal_id = #{waitDealId,jdbcType=VARCHAR}
  </update>
  <update id="updateByPrimaryKey" parameterType="com.my.color.wait.dao.po.WaitDeal">
    <!--
      WARNING - @mbg.generated
      This element is automatically generated by MyBatis Generator, do not modify.
    -->
    update e_wait_deal
    set wait_reference_id = #{waitReferenceId,jdbcType=VARCHAR},
      wait_instructor_uid = #{waitInstructorUid,jdbcType=VARCHAR},
      wait_instructor_uname = #{waitInstructorUname,jdbcType=VARCHAR},
      wait_student_uid = #{waitStudentUid,jdbcType=VARCHAR},
      wait_student_uname = #{waitStudentUname,jdbcType=VARCHAR},
      wait_class_id = #{waitClassId,jdbcType=VARCHAR},
      wait_class_name = #{waitClassName,jdbcType=VARCHAR},
      wait_is_vaild = #{waitIsVaild,jdbcType=VARCHAR},
      wait_deal_state = #{waitDealState,jdbcType=VARCHAR},
      wait_create_time = #{waitCreateTime,jdbcType=VARCHAR},
      wait_reply_result = #{waitReplyResult,jdbcType=VARCHAR},
      wait_reply_time = #{waitReplyTime,jdbcType=VARCHAR}
    where wait_deal_id = #{waitDealId,jdbcType=VARCHAR}
  </update>
  
  <select id="getWaitDealList" parameterType="java.lang.String" resultMap="BaseResultMap">
    <!--
      WARNING - @mbg.generated
      This element is automatically generated by MyBatis Generator, do not modify.
    -->
    select 
    <include refid="Base_Column_List" />
    from e_wait_deal
    where wait_is_vaild = '1' 
    and wait_instructor_uid = #{userId,jdbcType=VARCHAR}
    order by wait_create_time,wait_deal_state desc
  </select>
</mapper>